odoo/addons/account_ecotax_sale/README.rst
odoo/addons/account_ecotax_sale/__init__.py
odoo/addons/account_ecotax_sale/__manifest__.py
odoo/addons/account_ecotax_sale/hook.py
odoo/addons/account_ecotax_sale/i18n/account_ecotax_sale.pot
odoo/addons/account_ecotax_sale/i18n/account_ecotaxe_sale.pot
odoo/addons/account_ecotax_sale/i18n/fr.po
odoo/addons/account_ecotax_sale/i18n/it.po
odoo/addons/account_ecotax_sale/models/__init__.py
odoo/addons/account_ecotax_sale/models/sale_order.py
odoo/addons/account_ecotax_sale/models/sale_order_line.py
odoo/addons/account_ecotax_sale/models/sale_order_line_ecotax.py
odoo/addons/account_ecotax_sale/readme/CONTRIBUTORS.md
odoo/addons/account_ecotax_sale/readme/DESCRIPTION.md
odoo/addons/account_ecotax_sale/security/ir.model.access.csv
odoo/addons/account_ecotax_sale/static/description/icon.png
odoo/addons/account_ecotax_sale/static/description/index.html
odoo/addons/account_ecotax_sale/tests/__init__.py
odoo/addons/account_ecotax_sale/tests/test_sale_ecotax.py
odoo/addons/account_ecotax_sale/views/sale_view.xml
odoo_addon_account_ecotax_sale-17.0.1.0.2.dist-info/METADATA
odoo_addon_account_ecotax_sale-17.0.1.0.2.dist-info/WHEEL
odoo_addon_account_ecotax_sale-17.0.1.0.2.dist-info/top_level.txt
odoo_addon_account_ecotax_sale-17.0.1.0.2.dist-info/RECORD
